pyMSpec
