Metadata-Version: 1.0
Name: pyMSpec
Version: 0.1.2
Summary: Python library for processing individual mass spectra
Home-page: https://github.com/alexandrovteam/pyMSpec
Author: Alexandrov Team, EMBL
Author-email: UNKNOWN
License: UNKNOWN
Platform: UNKNOWN
